LICENSE
README.md
pyproject.toml
setup.py
dgeontology/__init__.py
dgeontology/dgeontology.py
dgeontology.egg-info/PKG-INFO
dgeontology.egg-info/SOURCES.txt
dgeontology.egg-info/dependency_links.txt
dgeontology.egg-info/requires.txt
dgeontology.egg-info/top_level.txt