Metadata-Version: 2.1
Name: dgeontology
Version: 1.0.0
Summary: Library for gene set enrichment analysis (ontology analysis) and visualisation
Home-page: https://github.com/michalbukowski/dge-ontology
Author: Michal Bukowski
Author-email: michal.bukowski@tuta.io
Project-URL: Bug Tracker, https://github.com/michalbukowski/dge-ontology/issues
Classifier: Intended Audience :: Science/Research
Classifier: Programming Language :: Python :: 3
Classifier: License :: OSI Approved :: GNU General Public License v3 (GPLv3)
Classifier: Operating System :: OS Independent
Requires-Python: >=3.6
License-File: LICENSE
Requires-Dist: pandas>=2.2
Requires-Dist: matplotlib>=3.8
Requires-Dist: scipy>=1.12
